{"authorDailyContributionsMap":{"jonasongg":[{"date":"2023-08-21","commitResults":[{"hash":"701f562291c9369769678720e3c1b0b5c0724810","isMergeCommit":false,"messageTitle":"change greeting message","messageBody":"","tags":["Level-0"],"fileTypesAndContributionMap":{"java":{"insertions":7,"deletions":6}}},{"hash":"b3cd12de7d1667992b04662829a860d2bbdf60d2","isMergeCommit":false,"messageTitle":"add scanner for entering commands","messageBody":"","fileTypesAndContributionMap":{"java":{"insertions":14,"deletions":1}}},{"hash":"fd258dcc96e2b462f6dbd6f13b46fe68eda0daba","isMergeCommit":false,"messageTitle":"create constant for horizontal line","messageBody":"","tags":["Level-1"],"fileTypesAndContributionMap":{"java":{"insertions":4,"deletions":8}}},{"hash":"e8ccacd566d9c847f0b7e35874c792934a518a01","isMergeCommit":false,"messageTitle":"add ability to store text and list them when requested","messageBody":"","tags":["Level-2"],"fileTypesAndContributionMap":{"java":{"insertions":12,"deletions":2}}},{"hash":"b23236221cbde144601e4af95a65d81cb2c6691a","isMergeCommit":false,"messageTitle":"add Task class","messageBody":"","fileTypesAndContributionMap":{"java":{"insertions":16,"deletions":4}}},{"hash":"82510b2adeb4bff5592e6957e045762c262d0f4f","isMergeCommit":false,"messageTitle":"add ability to mark and unmark tasks as done","messageBody":"","fileTypesAndContributionMap":{"java":{"insertions":16,"deletions":0}}}]},{"date":"2023-08-23","commitResults":[{"hash":"aab5c4f9b4265ccca8181cbd5e3edefa35442617","isMergeCommit":false,"messageTitle":"change to use switch case instead of if else","messageBody":"","fileTypesAndContributionMap":{"java":{"insertions":29,"deletions":20}}},{"hash":"233fd49ae76c0b47963154e7cfb8d830872c4cab","isMergeCommit":false,"messageTitle":"refactor outputting message into its own function","messageBody":"","tags":["Level-3"],"fileTypesAndContributionMap":{"java":{"insertions":13,"deletions":17}}},{"hash":"bb457b361f4388a7338f9deb97a77e494164e43a","isMergeCommit":false,"messageTitle":"add Todo class and change output messages","messageBody":"","fileTypesAndContributionMap":{"java":{"insertions":33,"deletions":13}}},{"hash":"ff056ee520be8e422bc4ba1bd5ddde54e182e810","isMergeCommit":false,"messageTitle":"add Deadline class","messageBody":"","fileTypesAndContributionMap":{"java":{"insertions":21,"deletions":0}}},{"hash":"ab420cb499daaa7944a30f47255923642f606ecf","isMergeCommit":false,"messageTitle":"add Event class","messageBody":"","tags":["Level-4"],"fileTypesAndContributionMap":{"java":{"insertions":24,"deletions":0}}},{"hash":"a1eeaa4ae41124ebceb37baa0c93780d825a17b7","isMergeCommit":false,"messageTitle":"add automated testing and fix inconsistencies","messageBody":"","tags":["A-TextUiTesting"],"fileTypesAndContributionMap":{"txt":{"insertions":7,"deletions":0},"java":{"insertions":8,"deletions":6}}},{"hash":"be00872dc2470eaa6b86512f83ee81c4ee2f8e1e","isMergeCommit":false,"messageTitle":"add basic error support","messageBody":"","tags":["Level-5"],"fileTypesAndContributionMap":{"java":{"insertions":11,"deletions":2}}},{"hash":"c75a101089bae83d25e9eaaa407d79c45d0a9745","isMergeCommit":false,"messageTitle":"add delete command","messageBody":"","tags":["Level-6","A-Collections"],"fileTypesAndContributionMap":{"java":{"insertions":7,"deletions":0}}}]},{"date":"2023-08-24","commitResults":[{"hash":"83fbc2beaa91dda7f9a8ce948356cb8a9c1f708e","isMergeCommit":false,"messageTitle":"close scanner when bye","messageBody":"","fileTypesAndContributionMap":{"java":{"insertions":1,"deletions":0}}}]},{"date":"2023-08-28","commitResults":[{"hash":"efb5adf4da70f4ca468757678dda67740d0233a4","isMergeCommit":false,"messageTitle":"implement saving data to file","messageBody":"","fileTypesAndContributionMap":{"java":{"insertions":32,"deletions":3}}},{"hash":"2ee3d008357f39b5bd9e1924af5b550110385ff6","isMergeCommit":false,"messageTitle":"implement loading data to file","messageBody":"","tags":["Level-7"],"fileTypesAndContributionMap":{"java":{"insertions":69,"deletions":18}}}]},{"date":"2023-08-29","commitResults":[{"hash":"04158e3c1ecda7a50822040d48f3424055a45f68","isMergeCommit":false,"messageTitle":"implement datetime parsing and displaying","messageBody":"","tags":["Level-8"],"fileTypesAndContributionMap":{"java":{"insertions":104,"deletions":86}}},{"hash":"84296d1efc0b097c0823413278e3d2e33f3e8fb8","isMergeCommit":false,"messageTitle":"refactor loading from file","messageBody":"","fileTypesAndContributionMap":{"java":{"insertions":5,"deletions":3}}},{"hash":"735fd93561b5e31dd64886255efc7eb7de6c126b","isMergeCommit":false,"messageTitle":"refactor storage into its own class","messageBody":"","fileTypesAndContributionMap":{"java":{"insertions":151,"deletions":117}}},{"hash":"90590b05791fd82a2ea53fa0df858f585f17dc17","isMergeCommit":false,"messageTitle":"refactor TaskList into its own class","messageBody":"","fileTypesAndContributionMap":{"java":{"insertions":57,"deletions":23}}},{"hash":"0936528ec9998a12fdfeea52d5ffc352b163d216","isMergeCommit":false,"messageTitle":"refactor ui into its own class","messageBody":"","fileTypesAndContributionMap":{"java":{"insertions":102,"deletions":55}}},{"hash":"8f1ee3096efa84a366b21b17e3b30c79d50fee9a","isMergeCommit":false,"messageTitle":"add Command classes","messageBody":"","fileTypesAndContributionMap":{"java":{"insertions":61,"deletions":1}}},{"hash":"38a70d2f536f5b44b71d5dd7291b24645af9abdf","isMergeCommit":false,"messageTitle":"add parser and integrate with commands","messageBody":"","fileTypesAndContributionMap":{"java":{"insertions":90,"deletions":62}}},{"hash":"1b778e08190324931aac8ea296db82e5087e20ac","isMergeCommit":false,"messageTitle":"fix index bug for delete and un/mark","messageBody":"","tags":["A-MoreOOP"],"fileTypesAndContributionMap":{"java":{"insertions":3,"deletions":3}}},{"hash":"77e8c595574aa4fc63a4704c3994745b1a243e60","isMergeCommit":false,"messageTitle":"add exceptions","messageBody":"","fileTypesAndContributionMap":{"java":{"insertions":50,"deletions":28}}},{"hash":"666bd9aa2e0b7fee6142cb439dbaff4eaaf5d4a7","isMergeCommit":false,"messageTitle":"add IllegalArgumentsExceptions for all tasks","messageBody":"","fileTypesAndContributionMap":{"java":{"insertions":25,"deletions":0}}},{"hash":"62a876cb3d83c4271cc46f20b66dfac68bb63c99","isMergeCommit":false,"messageTitle":"add exception for out-of-bounds task index","messageBody":"","tags":["A-Exceptions"],"fileTypesAndContributionMap":{"java":{"insertions":28,"deletions":11}}},{"hash":"777e7212e151cf9778df4214e1aec1468dbc6a0a","isMergeCommit":false,"messageTitle":"refactor all files to packages","messageBody":"","tags":["A-Packages"],"fileTypesAndContributionMap":{"java":{"insertions":100,"deletions":2}}}]}]},"authorFileTypeContributionMap":{"jonasongg":{"java":609,"md":0,"fxml":0,"sh":0,"bat":0,"gradle":0,"txt":7}},"authorContributionVariance":{"jonasongg":101537.9},"authorDisplayNameMap":{"jonasongg":"CS2103T-W15-3 JONA.. WEI"}}
