{"authorDailyContributionsMap":{"ktzy0305":[{"date":"2023-08-20","commitResults":[{"hash":"2653b7cbcdcc61a9a4e4ec1130a6129051c9d608","isMergeCommit":false,"messageTitle":"rename, greet, exit","messageBody":"","tags":["Level-0"],"fileTypesAndContributionMap":{"java":{"insertions":12,"deletions":7}}},{"hash":"1d0ba10b375026088c02f1d2208141e3b782928e","isMergeCommit":false,"messageTitle":"add echo functionality","messageBody":"","tags":["Level-1"],"fileTypesAndContributionMap":{"java":{"insertions":25,"deletions":7}}}]},{"date":"2023-08-21","commitResults":[{"hash":"cc8b300e9c1d41128db4c524a650193febbb74b8","isMergeCommit":false,"messageTitle":"feat: add task and list tasks","messageBody":"","tags":["Level-2"],"fileTypesAndContributionMap":{"java":{"insertions":42,"deletions":9}}},{"hash":"94e1fb634b7ab0b6838f721722c541564d1b77fc","isMergeCommit":false,"messageTitle":"add task.java","messageBody":"","tags":["A-Classes"],"fileTypesAndContributionMap":{"java":{"insertions":49,"deletions":0}}},{"hash":"ccdcf30b1f618a86da6a271f9b2109c94515373b","isMergeCommit":false,"messageTitle":"feat: add mark as done and unmark","messageBody":"","tags":["Level-3"],"fileTypesAndContributionMap":{"java":{"insertions":54,"deletions":8}}},{"hash":"0b5f0e4307643a0c1063be349ef6d63230c32caf","isMergeCommit":false,"messageTitle":"add classes Deadline.java, Event.java and ToDo.java","messageBody":"","tags":["A-Inheritance"],"fileTypesAndContributionMap":{"java":{"insertions":62,"deletions":0}}},{"hash":"9fa07a0ba9241ba3f7760d07c60bcddbcd73143a","isMergeCommit":false,"messageTitle":"feat: add todos, events and deadlines","messageBody":"","tags":["Level-4"],"fileTypesAndContributionMap":{"java":{"insertions":69,"deletions":18}}},{"hash":"2fb08c47f7e2143c488e6e8cdeccd3dc4771d821","isMergeCommit":false,"messageTitle":"add test inputs and expected outputs","messageBody":"","tags":["A-TextUiTesting"],"fileTypesAndContributionMap":{"txt":{"insertions":10,"deletions":0},"java":{"insertions":4,"deletions":3}}},{"hash":"a8a4980cd366e864a59f97ed93c13e12e6d439b5","isMergeCommit":false,"messageTitle":"Add DukeException.java","messageBody":"","tags":["A-Exceptions"],"fileTypesAndContributionMap":{"java":{"insertions":5,"deletions":0}}},{"hash":"60c284a3f3aee6ccc73a5081277b07f2c7e72ba7","isMergeCommit":false,"messageTitle":"Add error handling for incorrect inputs","messageBody":"","tags":["Level-5"],"fileTypesAndContributionMap":{"txt":{"insertions":3,"deletions":0},"java":{"insertions":159,"deletions":96}}},{"hash":"1bc59f4a45699a1ea3f2419a050b49d4bd9425d6","isMergeCommit":false,"messageTitle":"Add support for deleting tasks from the list","messageBody":"","tags":["Level-6","A-Enums","A-Collections"],"fileTypesAndContributionMap":{"txt":{"insertions":4,"deletions":0},"java":{"insertions":92,"deletions":47}}}]},{"date":"2023-08-28","commitResults":[{"hash":"165465e9342317ec369663a71345fa1af5dbc2f6","isMergeCommit":false,"messageTitle":"add functionality to save tasks","messageBody":"","fileTypesAndContributionMap":{"txt":{"insertions":1,"deletions":0},"java":{"insertions":256,"deletions":140}}},{"hash":"d1f9460a89fb23fedcf22f41ce35a1b2fa492642","isMergeCommit":true,"messageTitle":"Merge branch \u0027branch-Level-7\u0027","messageBody":"","tags":["Level-7"],"fileTypesAndContributionMap":{}},{"hash":"ff3eaab99e90fb360599fc4056a4a25940a1876f","isMergeCommit":false,"messageTitle":"add dates and times to Skye","messageBody":"","fileTypesAndContributionMap":{"txt":{"insertions":5,"deletions":1},"java":{"insertions":104,"deletions":24}}},{"hash":"c968518199dba50bac3bdbb95b757b5d90c59464","isMergeCommit":true,"messageTitle":"Merge branch \u0027branch-Level-8\u0027","messageBody":"","tags":["Level-8"],"fileTypesAndContributionMap":{}},{"hash":"6806c136c8d6237bdfd55adc7868fbd543efea08","isMergeCommit":false,"messageTitle":"remove data/tasks.txt","messageBody":"","fileTypesAndContributionMap":{"txt":{"insertions":0,"deletions":5}}}]},{"date":"2023-08-30","commitResults":[{"hash":"7aa1874ac85c641a11a8bfd183f24ed4ce5cfc2c","isMergeCommit":false,"messageTitle":"add more OOP","messageBody":"","tags":["A-MoreOOP"],"fileTypesAndContributionMap":{"txt":{"insertions":2,"deletions":0},"java":{"insertions":546,"deletions":289}}},{"hash":"70f4790e5c670637e33599e8150a8e7c47712eb9","isMergeCommit":false,"messageTitle":"add packaging of classes","messageBody":"","fileTypesAndContributionMap":{"java":{"insertions":129,"deletions":93}}},{"hash":"93771fd2cf91f90234596c675c0e6af74df523f8","isMergeCommit":true,"messageTitle":"Merge branch \u0027branch-Packages\u0027","messageBody":"","tags":["A-Packages"],"fileTypesAndContributionMap":{}},{"hash":"62d5a79cc490fe0d8b3b7e279c5d56dca36494db","isMergeCommit":true,"messageTitle":"Merge remote-tracking branch \u0027origin/add-gradle-support\u0027 into branch-JUnit","messageBody":"","fileTypesAndContributionMap":{}},{"hash":"4386f05b81b22cf9e5e9f44761532f449393d1f1","isMergeCommit":false,"messageTitle":"adds gradle build scripts, JUnit tests and create jar file","messageBody":"","fileTypesAndContributionMap":{"gradle":{"insertions":1,"deletions":1},"txt":{"insertions":0,"deletions":2},"java":{"insertions":318,"deletions":107},"bat":{"insertions":3,"deletions":3},"sh":{"insertions":2,"deletions":2},"md":{"insertions":2,"deletions":2}}},{"hash":"1e3f626e4a5c12e4e38a6233df73e1b2cdf8dc9b","isMergeCommit":true,"messageTitle":"Merge branch \u0027branch-JUnit\u0027","messageBody":"","tags":["A-Jar","A-JUnit","A-Gradle"],"fileTypesAndContributionMap":{}}]},{"date":"2023-08-31","commitResults":[{"hash":"6fbfbac718a63e43bb243ff76cd6b7cb460c75bc","isMergeCommit":false,"messageTitle":"adhere to Java coding standards.","messageBody":"","fileTypesAndContributionMap":{"java":{"insertions":105,"deletions":53}}},{"hash":"e1553b7aea1287e5f90f420984a57c4ee2990c7a","isMergeCommit":false,"messageTitle":"Add JavaDoc documentation for classes and methods","messageBody":"","fileTypesAndContributionMap":{"java":{"insertions":585,"deletions":25}}},{"hash":"c35b8f8b12d704155271de0b873c714ce116fe6c","isMergeCommit":false,"messageTitle":"add find task command","messageBody":"","fileTypesAndContributionMap":{"txt":{"insertions":26,"deletions":0},"java":{"insertions":107,"deletions":7}}},{"hash":"e7468cdef573d4adb57d51eae25d654e59609327","isMergeCommit":true,"messageTitle":"Merge branch \u0027branch-Level-9\u0027","messageBody":"","fileTypesAndContributionMap":{}},{"hash":"58f31431e2a44830e05b80824e95047d3754de7a","isMergeCommit":true,"messageTitle":"Merge branch \u0027branch-A-CodingStandard\u0027","messageBody":"# Conflicts:\n#\tsrc/main/java/duke/parser/Parser.java\n#\tsrc/main/java/duke/ui/UI.java\n","fileTypesAndContributionMap":{}},{"hash":"1ad25962e0583d5cf0d9b4430bb61c0e13608256","isMergeCommit":true,"messageTitle":"Merge branch \u0027branch-A-JavaDoc\u0027","messageBody":"# Conflicts:\n#\tsrc/main/java/duke/Duke.java\n#\tsrc/main/java/duke/commands/Command.java\n#\tsrc/main/java/duke/commands/DueCommand.java\n#\tsrc/main/java/duke/commands/HelpCommand.java\n#\tsrc/main/java/duke/commands/ListCommand.java\n#\tsrc/main/java/duke/data/TaskList.java\n#\tsrc/main/java/duke/data/exception/DukeException.java\n#\tsrc/main/java/duke/parser/Parser.java\n#\tsrc/main/java/duke/storage/Storage.java\n#\tsrc/main/java/duke/ui/UI.java\n","tags":["Level-9","A-JavaDoc","A-CodingStandard"],"fileTypesAndContributionMap":{}}]},{"date":"2023-09-03","commitResults":[{"hash":"d4862747c60b7e98cb6c9a3c09a87d0c0d75e3d0","isMergeCommit":true,"messageTitle":"Merge branch \u0027master\u0027 into branch-JUnit","messageBody":"","fileTypesAndContributionMap":{}},{"hash":"9cb103b6faf4d7a8c0dbb97c107df03692288d63","isMergeCommit":false,"messageTitle":"add unit test cases for TaskDecoder.java","messageBody":"","fileTypesAndContributionMap":{"java":{"insertions":72,"deletions":3}}},{"hash":"cbb16d531151fb252297ba1af334fb248a3a78d6","isMergeCommit":true,"messageTitle":"Merge branch \u0027branch-JUnit\u0027","messageBody":"","fileTypesAndContributionMap":{}},{"hash":"f37785136cdff0b3a07de74dd15fe6895d29cc16","isMergeCommit":true,"messageTitle":"Merge branch \u0027master\u0027 into branch-Packages","messageBody":"","fileTypesAndContributionMap":{}},{"hash":"b862a45325da19a083ccd51da4619395199f6cc7","isMergeCommit":false,"messageTitle":"rename package name from duke to skye","messageBody":"","fileTypesAndContributionMap":{"gradle":{"insertions":2,"deletions":2},"txt":{"insertions":0,"deletions":0},"java":{"insertions":136,"deletions":134},"bat":{"insertions":3,"deletions":3},"md":{"insertions":2,"deletions":2}}},{"hash":"2b2b19b3a665a5eccca4966c1f19afac277436d5","isMergeCommit":true,"messageTitle":"Merge branch \u0027branch-Packages\u0027","messageBody":"","fileTypesAndContributionMap":{}}]},{"date":"2023-09-04","commitResults":[{"hash":"690dd24c6082086f4fab12de0024b22123a1bc2a","isMergeCommit":false,"messageTitle":"update readme title","messageBody":"","fileTypesAndContributionMap":{"txt":{"insertions":3,"deletions":3},"md":{"insertions":1,"deletions":1}}}]},{"date":"2023-09-05","commitResults":[{"hash":"3de268a783a333f13c326d654c6b6ef352c93349","isMergeCommit":false,"messageTitle":"add checkstyle to the project and change import order","messageBody":"","fileTypesAndContributionMap":{"gradle":{"insertions":5,"deletions":0},"java":{"insertions":140,"deletions":121}}},{"hash":"607d00dbadd6a7b4e471c049431806d67b75755c","isMergeCommit":true,"messageTitle":"Merge branch \u0027branch-A-CheckStyle\u0027","messageBody":"","tags":["A-CheckStyle"],"fileTypesAndContributionMap":{}}]},{"date":"2023-09-07","commitResults":[{"hash":"2fcda70ca7e349607c584786967ff97e5ba4bb00","isMergeCommit":false,"messageTitle":"Add a GUI to the Skye chatbot","messageBody":"","fileTypesAndContributionMap":{"gradle":{"insertions":15,"deletions":0},"fxml":{"insertions":48,"deletions":0},"java":{"insertions":293,"deletions":47}}},{"hash":"d563c490f2591889ddc608f3dfc6e35e6dc9f3f6","isMergeCommit":true,"messageTitle":"Merge branch \u0027branch-Level-10\u0027","messageBody":"","tags":["Level-10"],"fileTypesAndContributionMap":{}}]},{"date":"2023-09-13","commitResults":[{"hash":"882e988f50802fb580daa223b74d62287a09f35a","isMergeCommit":false,"messageTitle":"Improve code quality and fix coding standard violations","messageBody":"Improvements were made to the code quality of the existing code base.\n\nCoding standard violations regarding indentation of wrapped lines and javadoc comments were identified.\n\nA summary of what was done\n* Ensure that wrapped lines are indented by 8 spaces.\n* Ensure all naming complies with coding standards\n* Removal of dead code\n","tags":["A-Varargs","A-Streams","A-CodeQuality"],"fileTypesAndContributionMap":{"gradle":{"insertions":1,"deletions":1},"java":{"insertions":24,"deletions":12}}},{"hash":"5ecb3895b77ca30d034baa12e3bb69f06bfe9a54","isMergeCommit":false,"messageTitle":"Add assertion statements for decoder and parser","messageBody":"","tags":["A-Assertions"],"fileTypesAndContributionMap":{"gradle":{"insertions":1,"deletions":1},"java":{"insertions":8,"deletions":0}}},{"hash":"a1a7da70f6736d044abad226482e248ba48f32d1","isMergeCommit":true,"messageTitle":"Merge pull request #1 from ktzy0305/branch-A-Assertions","messageBody":"Add assertion statements for decoder and parser","fileTypesAndContributionMap":{}},{"hash":"c567e759cca48a721c557be1a50c4c0a5ffc98e6","isMergeCommit":true,"messageTitle":"Merge pull request #2 from ktzy0305/branch-A-CodeQuality","messageBody":"Improve code quality and fix coding standard violations","fileTypesAndContributionMap":{}}]},{"date":"2023-09-14","commitResults":[{"hash":"80c1da3252e4f2c6adcbe1c839f32ae38d7be88c","isMergeCommit":false,"messageTitle":"runtest.bat: Ammend entry point of application","messageBody":"Ammend entry point to reflect changes to the name of the application\n\nChanges:\n* Duke to Skye\n","fileTypesAndContributionMap":{"sh":{"insertions":2,"deletions":2}}},{"hash":"9d679d52ed72598f679665aff6cb8c46135c7fd7","isMergeCommit":false,"messageTitle":"Add functionality to record and manage places","messageBody":"As part of the extension features, Skye can now record venues you have\nin mind to book in the future.\n\nAssumptions (MVP)\n* Booking is for one entire day\n\nFuture Extensions\n* Using generics for storage and list\n","tags":["BCD-Extension"],"fileTypesAndContributionMap":{"txt":{"insertions":2,"deletions":0},"java":{"insertions":704,"deletions":99}}},{"hash":"e646bf45ac1dd5e53eee9ad228f61d3b15c46474","isMergeCommit":true,"messageTitle":"Merge pull request #3 from ktzy0305/branch-D-Places","messageBody":"Add functionality to record and manage places","fileTypesAndContributionMap":{}}]},{"date":"2023-09-18","commitResults":[{"hash":"c1d669965431c03dc9d03550409f788e95a611f8","isMergeCommit":false,"messageTitle":"Add resizing of window and tweak alignment of dialog box","messageBody":"","fileTypesAndContributionMap":{"fxml":{"insertions":12,"deletions":9},"java":{"insertions":17,"deletions":117}}}]},{"date":"2023-09-19","commitResults":[{"hash":"c646b736c6c9ae1156eeb69b7f68c700cbead60b","isMergeCommit":false,"messageTitle":"add layer of abstraction for storage","messageBody":"","fileTypesAndContributionMap":{"java":{"insertions":272,"deletions":193}}},{"hash":"13177d0e4980d8b0b79ce4b808cef38ca76010b3","isMergeCommit":false,"messageTitle":"update command usage and error messages","messageBody":"","fileTypesAndContributionMap":{"txt":{"insertions":10,"deletions":5},"java":{"insertions":39,"deletions":21}}},{"hash":"7d479909bbef5d54ebd015ea756349537c3c9e2f","isMergeCommit":true,"messageTitle":"Merge branch \u0027branch-A-BetterGui\u0027","messageBody":"","tags":["A-BetterGui"],"fileTypesAndContributionMap":{}},{"hash":"72304adc28433823ed049b1167bcd1b54a9aff98","isMergeCommit":false,"messageTitle":"restore bye command feature","messageBody":"","fileTypesAndContributionMap":{"java":{"insertions":30,"deletions":6}}},{"hash":"34e545bd9729379310a0945c01a45d42dc3d5d47","isMergeCommit":true,"messageTitle":"Merge branch \u0027master\u0027 into branch-A-Personality","messageBody":"","fileTypesAndContributionMap":{}},{"hash":"f09c15313ce96f66802d573eb53f494bd8376c20","isMergeCommit":false,"messageTitle":"change response message for some commands","messageBody":"","fileTypesAndContributionMap":{"java":{"insertions":3,"deletions":3}}},{"hash":"aea074b5c039beba7f1aec33515660ffcecd5b86","isMergeCommit":true,"messageTitle":"Merge branch \u0027branch-A-Personality\u0027","messageBody":"","tags":["A-Personality"],"fileTypesAndContributionMap":{}}]},{"date":"2023-09-20","commitResults":[{"hash":"54f8b0965c48ce13bc72ba135d093e777eaecf7e","isMergeCommit":false,"messageTitle":"Add User Guide V0.1","messageBody":"","fileTypesAndContributionMap":{"md":{"insertions":71,"deletions":9}}}]},{"date":"2023-09-21","commitResults":[{"hash":"b768f1414013445dc8ff04176fa8b3b2b1937d6e","isMergeCommit":false,"messageTitle":"update user guide to v1.0","messageBody":"","tags":["A-UserGuide"],"fileTypesAndContributionMap":{"java":{"insertions":3,"deletions":3},"md":{"insertions":208,"deletions":11}}},{"hash":"989a12054f95faf2c2cd208478076f08a8b4422a","isMergeCommit":true,"messageTitle":"Merge branch \u0027master\u0027 into branch-A-BetterGui","messageBody":"","fileTypesAndContributionMap":{}},{"hash":"93d2768f12956ac9f98e3914797afdc2b9286a04","isMergeCommit":false,"messageTitle":"Fix message truncation and formatting","messageBody":"","fileTypesAndContributionMap":{"txt":{"insertions":5,"deletions":2},"fxml":{"insertions":11,"deletions":2},"java":{"insertions":30,"deletions":5},"md":{"insertions":141,"deletions":156}}},{"hash":"87fb936aa6f0508193ded1abe54376b647c120f3","isMergeCommit":true,"messageTitle":"Merge branch \u0027branch-A-BetterGui\u0027","messageBody":"","fileTypesAndContributionMap":{}},{"hash":"7307eb765e738efe1e3047bf3ecc46009d63a8ae","isMergeCommit":false,"messageTitle":"Ammend comments to comply to code quality","messageBody":"","fileTypesAndContributionMap":{"java":{"insertions":1,"deletions":1}}},{"hash":"b49a848cd3f3292fb6a20187dd5d148ae8fdf876","isMergeCommit":false,"messageTitle":"Add test cases for VenueList.java and VenueDecoder.java","messageBody":"","fileTypesAndContributionMap":{"java":{"insertions":136,"deletions":1},"md":{"insertions":1,"deletions":6}}},{"hash":"8b5c1bd7243fd7189b5441991315c33c05b82d90","isMergeCommit":true,"messageTitle":"Merge branch \u0027branch-A-MoreTesting\u0027","messageBody":"","tags":["A-MoreTesting"],"fileTypesAndContributionMap":{}},{"hash":"3579e17e7be9a423d91978d3da5a7e0db33d94a1","isMergeCommit":false,"messageTitle":"Fix a bug where help command returns a file path","messageBody":"","tags":["A-Release"],"fileTypesAndContributionMap":{"txt":{"insertions":0,"deletions":0},"java":{"insertions":19,"deletions":4}}}]}]},"authorFileTypeContributionMap":{"ktzy0305":{"java":2981,"md":248,"fxml":60,"sh":3,"bat":3,"gradle":20,"txt":53}},"authorContributionVariance":{"ktzy0305":125082.36},"authorDisplayNameMap":{"ktzy0305":"CS2103-F13-3 KEVI..YING"}}
