{"authorDailyContributionsMap":{"proto-aiken-13":[{"date":"2023-08-22","commitResults":[{"hash":"a6e44e87053c73a5a7f7debf578cbe6a6d635e53","isMergeCommit":false,"messageTitle":"Level 0 of the iP + Added greeting and exit messages as a skeletal programme","messageBody":"","tags":["Level-0"],"fileTypesAndContributionMap":{"java":{"insertions":6,"deletions":6}}},{"hash":"ddca1fbad49c0a33a66d869859a866b9d9c2ec04","isMergeCommit":false,"messageTitle":"Level 1 of the iP + Added a messageHandler method that merely echoes the user\u0027s input messages.","messageBody":"","tags":["Level-1"],"fileTypesAndContributionMap":{"java":{"insertions":27,"deletions":0}}}]},{"date":"2023-08-23","commitResults":[{"hash":"44e2cccc1abee88ce51db852256ba9d02fe940e7","isMergeCommit":false,"messageTitle":"Level 2 of the iP + Edited the messageHandler method to store all tasks inputted by the user accordingly. + Added a new DukeList class that stores and manages all messages given by the user. + The DukeList class contains the store and display methods which stores tasks inputted by the user and displays them in a list accordingly.","messageBody":"","tags":["Level-2"],"fileTypesAndContributionMap":{"java":{"insertions":67,"deletions":11}}}]}]},"authorFileTypeContributionMap":{"proto-aiken-13":{"java":89,"md":0,"fxml":0,"sh":0,"bat":0,"gradle":0,"txt":0}},"authorContributionVariance":{"proto-aiken-13":887.25},"authorDisplayNameMap":{"proto-aiken-13":"JOSE..CENA"}}
