{"authorDailyContributionsMap":{"applepiofmyeye":[{"date":"2023-08-23","commitResults":[{"hash":"caaeced440ab911e6e4ac4e39e4f55de5f63d954","isMergeCommit":false,"messageTitle":"Level 0","messageBody":"","tags":["Level-0"],"fileTypesAndContributionMap":{"java":{"insertions":11,"deletions":6}}},{"hash":"d63db97a9f9a47182b396f29f77e3db592049cbc","isMergeCommit":false,"messageTitle":"Commit message for Tag-1","messageBody":"","fileTypesAndContributionMap":{"java":{"insertions":50,"deletions":1}}},{"hash":"fd1e6897eefb156971a6fd3dd791f98d94339d5f","isMergeCommit":false,"messageTitle":"Code recovery","messageBody":"","fileTypesAndContributionMap":{"java":{"insertions":1,"deletions":50}}},{"hash":"124fa157e977274158057958aba242ae78c2d134","isMergeCommit":false,"messageTitle":"Level-2: Add, List","messageBody":"","tags":["Level-2"],"fileTypesAndContributionMap":{"java":{"insertions":50,"deletions":1}}},{"hash":"b4c7fedf690650dd0a2dc917749e378d4afade52","isMergeCommit":false,"messageTitle":"Level-1: Echo","messageBody":"","tags":["Level-1"],"fileTypesAndContributionMap":{"java":{"insertions":2,"deletions":16}}}]},{"date":"2023-08-25","commitResults":[{"hash":"f1e3964c29d583dbfd7d3e27df05db309e90a294","isMergeCommit":false,"messageTitle":"Level-3: Mark as done, created new class Task","messageBody":"","tags":["Level-3"],"fileTypesAndContributionMap":{"java":{"insertions":116,"deletions":14}}},{"hash":"a15899d075831bb22eddafd40e1eee63941b0afc","isMergeCommit":false,"messageTitle":"Level-4: Todos, deadlines and barbie parties hehe","messageBody":"","tags":["Level-4"],"fileTypesAndContributionMap":{"java":{"insertions":91,"deletions":5},"md":{"insertions":18,"deletions":9}}},{"hash":"24d5936476f5e096bdfd7a217bc856c2e110e563","isMergeCommit":false,"messageTitle":"automated UI Testing","messageBody":"","tags":["A-TextUiTesting"],"fileTypesAndContributionMap":{"txt":{"insertions":8,"deletions":0},"java":{"insertions":5,"deletions":5},"sh":{"insertions":1,"deletions":1}}},{"hash":"e6154f2a556be6f79600c99ae7edbcf9e9cbf660","isMergeCommit":false,"messageTitle":"Level-5 Handle errors","messageBody":"","tags":["Level-5"],"fileTypesAndContributionMap":{"java":{"insertions":144,"deletions":120}}},{"hash":"9101f3402c76ad537d2248b52a28542ca3dfa433","isMergeCommit":false,"messageTitle":"not the best.. but Level-6 v1","messageBody":"","tags":["Level-6.1"],"fileTypesAndContributionMap":{"java":{"insertions":37,"deletions":24}}}]},{"date":"2023-08-28","commitResults":[{"hash":"45012ece5238ff3a80843036763844ab9792b040","isMergeCommit":false,"messageTitle":"A-Enums, using enums for commands, to inc readability","messageBody":"","tags":["A-Enums"],"fileTypesAndContributionMap":{"java":{"insertions":118,"deletions":103}}}]}]},"authorFileTypeContributionMap":{"applepiofmyeye":{"java":286,"md":17,"fxml":0,"sh":1,"bat":0,"gradle":0,"txt":8}},"authorContributionVariance":{"applepiofmyeye":31782.062},"authorDisplayNameMap":{"applepiofmyeye":"CS2103T-W12-2 JOEY..LEYI"}}
